LICENSE
MANIFEST.in
README.md
requirements.txt
setup.cfg
setup.py
usttc/__init__.py
usttc/config.py
usttc.egg-info/PKG-INFO
usttc.egg-info/SOURCES.txt
usttc.egg-info/dependency_links.txt
usttc.egg-info/requires.txt
usttc.egg-info/top_level.txt
usttc/asr_client/__init__.py
usttc/asr_client/asr_client.py
usttc/asr_client/asr_client_factory.py
usttc/asr_client/asr_client_interface.py
usttc/asr_client/asr_provider.py
usttc/asr_client/assembly_ai_client.py
usttc/asr_client/aws_client.py
usttc/asr_client/azure_client.py
usttc/asr_client/deepgram_client.py
usttc/asr_client/ensemble_asr_client.py
usttc/asr_client/google_client.py
usttc/asr_client/multi_asr_client.py
usttc/asr_client/rev_client.py
usttc/asr_client/riva_client.py
usttc/asr_client/voicegain_client.py
usttc/audio/__init__.py
usttc/audio/audio_file.py
usttc/ensemble/__init__.py
usttc/ensemble/basic_edit_distance.py
usttc/ensemble/comparable_diff_word.py
usttc/ensemble/comparable_phrase.py
usttc/ensemble/comparable_result.py
usttc/ensemble/comparable_word.py
usttc/ensemble/ensemble.py
usttc/exceptions/__init__.py
usttc/exceptions/exceptions.py
usttc/result/__init__.py
usttc/result/paragraph.py
usttc/result/recognize_result.py
usttc/result/text_unit.py
usttc/result/word.py
usttc/stream/__init__.py
usttc/stream/microphone_stream.py
usttc/stream/stream.py
usttc/stream/stream_results.py
usttc/utils/__init__.py
usttc/utils/utils.py