Metadata-Version: 2.1
Name: usttc
Version: 0.0.7
Summary: Unified Speech-to-text Client
Download-URL: https://github.com/kakakuoka/usttc/archive/refs/tags/v0.0.7.tar.gz
Author: Kuo Zhang
Author-email: kuo.zh92@gmail.com
License-File: LICENSE
